{"cameraMode":{"drawMode":0,"name":"Shaded","section":"Shading Mode"},"sceneLighting":true,"audioPlay":false,"sceneViewState":{"showFog":false,"showMaterialUpdate":false,"showSkybox":false,"showFlares":false,"showImageEffects":false,"showParticleSystems":false,"showVisualEffectGraphs":true,"m_FxEnabled":true},"in2DMode":false,"pivot":{"x":3.735219955444336,"y":2.9192278385162355,"z":-7.074275970458984},"rotation":{"x":-0.15565034747123719,"y":-0.01897813193500042,"z":0.00302069541066885,"w":-0.9876738786697388},"size":12.12435531616211,"orthographic":false}